practice/restart_8_2_26/generic.v
/* Generated by Yosys 0.9 (git sha1 1979e0b) */

(* top =  1  *)
(* src = "xorgate.v:1" *)
module xorgate(in1, in2, out1);
  (* src = "xorgate.v:2" *)
  input in1;
  (* src = "xorgate.v:2" *)
  input in2;
  (* src = "xorgate.v:3" *)
  output out1;
  assign out1 = in2 ^ in1;
endmodule

practice/restart_8_2_26/xorgatetb.v
module xorgatetb;
reg in1 , in2 ;
wire out1 ;

xorgate x1 (
.in1(in1),.in2(in2),.out1(out1));

initial begin 
$dumpfile ("xor1.vcd");
$dumpvars ( 0 , xorgatetb);
repeat (100) begin 
in1 = $random%2 ;
in2 = $random %2 ;
#20 ;
end 
end 
endmodule

practice/restart_8_2_26/xor1.vcd
$date
	Sun Feb  8 18:01:37 2026
$end
$version
	Icarus Verilog
$end
$timescale
	1s
$end
$scope module xorgatetb $end
$var wire 1 ! out1 $end
$var reg 1 " in1 $end
$var reg 1 # in2 $end
$scope module x1 $end
$var wire 1 " in1 $end
$var wire 1 # in2 $end
$var wire 1 ! out1 $end
$upscope $end
$upscope $end
$enddefinitions $end
#0
$dumpvars
1#
0"
1!
$end
#20
0!
1"
#60
1!
0#
#80
0!
1#
#100
1!
0"
#120
0#
1"
#180
0!
1#
#200
1!
0"
#220
0!
0#
#240
1!
1#
#280
0!
1"
#300
1!
0#
#320
0!
0"
#340
1!
1#
#380
0!
1"
#420
0#
0"
#440
1#
1"
#460
1!
0#
#480
0!
0"
#520
1!
1"
#540
1#
0"
#560
0#
1"
#580
0!
0"
#620
1#
1"
#660
1!
0#
#680
1#
0"
#700
0!
1"
#720
0#
0"
#740
1#
1"
#760
1!
0"
#780
0#
1"
#800
0!
1#
#820
1!
0#
#840
0!
1#
#860
0#
0"
#900
1#
1"
#920
0#
0"
#940
1#
1"
#980
1!
0#
#1000
0!
1#
#1020
1!
0#
#1040
0!
0"
#1100
1#
1"
#1140
1!
0#
#1160
0!
1#
#1180
0#
0"
#1200
1#
1"
#1220
1!
0"
#1240
0!
1"
#1260
1!
0#
#1280
0!
0"
#1300
1!
1"
#1320
0!
0"
#1340
1#
1"
#1360
0#
0"
#1380
1!
1"
#1400
0!
0"
#1420
1!
1"
#1440
1#
0"
#1480
0!
1"
#1520
0#
0"
#1540
1!
1#
#1560
0!
0#
#1580
1#
1"
#1600
0#
0"
#1620
1!
1#
#1640
0#
1"
#1660
0!
0"
#1680
1#
1"
#1700
0#
0"
#1720
1!
1#
#1740
0!
0#
#1760
1!
1"
#1780
0!
0"
#1800
1!
1"
#1820
0!
1#
#1840
0#
0"
#1880
1!
1"
#1900
0!
0"
#1920
1!
1#
#1940
0!
1"
#1960
1!
0"
#1980
0!
1"
